fileresponse/__init__.py
fileresponse/_nbdev.py
fileresponse/asgi.py
fileresponse/core.py
fileresponse/handlers.py
fileresponse/http.py
fileresponse/scripts.py
django_fileresponse-0.1.0.dist-info/LICENSE
django_fileresponse-0.1.0.dist-info/METADATA
django_fileresponse-0.1.0.dist-info/WHEEL
django_fileresponse-0.1.0.dist-info/entry_points.txt
django_fileresponse-0.1.0.dist-info/top_level.txt
django_fileresponse-0.1.0.dist-info/RECORD
