Metadata-Version: 2.1
Name: django-fileresponse
Version: 0.1.0
Summary: Serving files directly from Django
Home-page: https://github.com/ephes/django_fileresponse/tree/main/
Author: Jochen Wersdörfer
Author-email: jochen-djangofileresponse@wersdoerfer.de
License: Apache Software License 2.0
Keywords: web nbdev async asyncio Django asgi wsgi
Platform: UNKNOWN
Classifier: Development Status :: 3 - Alpha
Classifier: Intended Audience :: Developers
Classifier: Natural Language :: English
Classifier: Programming Language :: Python :: 3.6
Classifier: Programming Language :: Python :: 3.7
Classifier: Programming Language :: Python :: 3.8
Classifier: License :: OSI Approved :: Apache Software License
Requires-Python: >=3.6
Requires-Dist: pip
Requires-Dist: packaging
Requires-Dist: Django (>=3.1)
Requires-Dist: aiofiles
Requires-Dist: aiobotocore
Provides-Extra: dev
Requires-Dist: nbdev ; extra == 'dev'
Requires-Dist: django-extensions ; extra == 'dev'
Requires-Dist: uvicorn[standard] ; extra == 'dev'
Requires-Dist: gunicorn ; extra == 'dev'
Requires-Dist: nb-black ; extra == 'dev'
Requires-Dist: pandas ; extra == 'dev'
Requires-Dist: matplotlib ; extra == 'dev'
Requires-Dist: gevent ; extra == 'dev'
Requires-Dist: httpx ; extra == 'dev'
Requires-Dist: requests ; extra == 'dev'
Requires-Dist: minio ; extra == 'dev'
Requires-Dist: aiohttp (<4) ; extra == 'dev'
